MANIFEST.in
README.md
setup.py
xFlask.egg-info/PKG-INFO
xFlask.egg-info/SOURCES.txt
xFlask.egg-info/dependency_links.txt
xFlask.egg-info/requires.txt
xFlask.egg-info/top_level.txt
xflask/__init__.py
xflask/application.py
xflask/component.py
xflask/context.py
xflask/dao.py
xflask/dto.py
xflask/exception.py
xflask/json.py
xflask/migrate.py
xflask/service.py
xflask/classy/__init__.py
xflask/classy/annotation.py
xflask/classy/flask_classy.py
xflask/common/__init__.py
xflask/common/configuration.py
xflask/common/logger.py
xflask/common/util/__init__.py
xflask/common/util/date_util.py
xflask/common/util/file_util.py
xflask/common/util/obj_util.py
xflask/common/util/shell_util.py
xflask/conf/logging.yml
xflask/conf/server.yml
xflask/sqlalchemy/__init__.py
xflask/sqlalchemy/decorator.py
xflask/sqlalchemy/model.py
xflask/sqlalchemy/util.py
xflask/type/__init__.py
xflask/type/enum.py
xflask/type/sys_code.py
xflask/web/__init__.py
xflask/web/controller.py
xflask/web/error_handler.py
xflask/web/filter.py
xflask/web/response.py
xflask/web/security/__init__.py
xflask/web/security/auth_manager.py
xflask/web/security/jwt_auth_filter.py
xflask/web/security/jwt_auth_manager.py
xflask/wtforms/__init__.py
xflask/wtforms/field.py
xflask/wtforms/form.py
xflask/wtforms/json.py
xflask/wtforms/validator.py