Metadata-Version: 2.1
Name: xFlask
Version: 0.2.2
Summary: Python Web Framework
Home-page: https://github.com/sotheara-leang/xFlask.git
Author: LEANG Sotheara
Author-email: leangsotheara@gmail.com
License: UNKNOWN
Keywords: xFlask,Restful,Web
Platform: UNKNOWN
Classifier: Development Status :: 3 - Alpha
Classifier: Intended Audience :: Developers
Classifier: License :: OSI Approved :: MIT License
Requires-Python: >=3.5
